quahris/__init__.py
quahris/functions.py
quahris-0.0.5.0.dist-info/LICENSE.txt
quahris-0.0.5.0.dist-info/METADATA
quahris-0.0.5.0.dist-info/WHEEL
quahris-0.0.5.0.dist-info/top_level.txt
quahris-0.0.5.0.dist-info/RECORD
