Metadata-Version: 2.1
Name: quahris
Version: 0.0.5.0
Summary: API Library for Qualys
Author: Chris Nam
License: MIT
License-File: LICENSE.txt
